voctokey/__init__.py
voctokey/__main__.py
voctokey/config.py
voctokey/tcp.py
voctokey-0.0.1.dist-info/METADATA
voctokey-0.0.1.dist-info/RECORD
voctokey-0.0.1.dist-info/WHEEL
voctokey-0.0.1.dist-info/entry_points.txt
voctokey-0.0.1.dist-info/top_level.txt
